setup.cfg
setup.py
metacontext/__init__.py
metacontext/template.py
metacontext/unparse.py
metacontext.egg-info/PKG-INFO
metacontext.egg-info/SOURCES.txt
metacontext.egg-info/dependency_links.txt
metacontext.egg-info/top_level.txt