Metadata-Version: 1.0
Name: metacontext
Version: 0.2.2
Summary: Metaprogramming with context managers
Home-page: https://github.com/mmikulicic/metacontext
Author: Marko Mikulicic
Author-email: mmikulicic@gmail.com
License: UNKNOWN
Platform: UNKNOWN
Classifier: License :: OSI Approved :: BSD License
Classifier: Intended Audience :: Developers
Classifier: Topic :: Software Development :: Libraries
Classifier: Topic :: Software Development :: Compilers
Classifier: Topic :: Software Development :: Code Generators
Classifier: Topic :: Software Development :: Pre-processors
